{
    "conversations": [
      {
        "id": "conv1",
        "timestamp": "2024-01-27T10:00:00Z",
        "user_interactions": [
          {
            "type": "text",
            "content": "Sample user question"
          },
          {
            "type": "image",
            "content": "path/to/image.jpg"
          },
          {
            "type": "pdf",
            "content": "path/to/document.pdf"
          },
          {
            "type": "audio",
            "content": "path/to/audio.mp3"
          }
        ],
        "ai_responses": [
          {
            "ai_id": "ai1",
            "response_type": "text",
            "content": "AI's text response"
          },
          {
            "ai_id": "ai2",
            "response_type": "image",
            "content": "path/to/generated_image.jpg"
          }
        ],
        "context": {
        },
        "memory": {
          "short_term": [
          ],
          "long_term": [
          ]
        }
      }
    ]
  }
  